google_datacatalog_hive_connector-0.9.0-py3.7-nspkg.pth
google/datacatalog_connectors/hive/__init__.py
google/datacatalog_connectors/hive/datacatalog_cli.py
google/datacatalog_connectors/hive/entities/__init__.py
google/datacatalog_connectors/hive/entities/base.py
google/datacatalog_connectors/hive/entities/column.py
google/datacatalog_connectors/hive/entities/database.py
google/datacatalog_connectors/hive/entities/sync_event.py
google/datacatalog_connectors/hive/entities/table.py
google/datacatalog_connectors/hive/entities/table_params.py
google/datacatalog_connectors/hive/entities/table_storage.py
google/datacatalog_connectors/hive/prepare/__init__.py
google/datacatalog_connectors/hive/prepare/assembled_entry_factory.py
google/datacatalog_connectors/hive/prepare/datacatalog_entry_factory.py
google/datacatalog_connectors/hive/scrape/__init__.py
google/datacatalog_connectors/hive/scrape/metadata_database_scraper.py
google/datacatalog_connectors/hive/scrape/metadata_sync_event_scraper.py
google/datacatalog_connectors/hive/sync/__init__.py
google/datacatalog_connectors/hive/sync/datacatalog_synchronizer.py
google_datacatalog_hive_connector-0.9.0.dist-info/METADATA
google_datacatalog_hive_connector-0.9.0.dist-info/WHEEL
google_datacatalog_hive_connector-0.9.0.dist-info/entry_points.txt
google_datacatalog_hive_connector-0.9.0.dist-info/namespace_packages.txt
google_datacatalog_hive_connector-0.9.0.dist-info/top_level.txt
google_datacatalog_hive_connector-0.9.0.dist-info/RECORD
