Metadata-Version: 2.1
Name: google-datacatalog-hive-connector
Version: 0.9.0
Summary: Library for ingesting Hive metadata into Google Cloud Data Catalog
Home-page: UNKNOWN
Author: Google LLC
License: UNKNOWN
Platform: Posix; MacOS X; Windows
Classifier: Development Status :: 4 - Beta
Classifier: Programming Language :: Python :: 3.7
Requires-Dist: psycopg2-binary
Requires-Dist: mysqlclient
Requires-Dist: sqlalchemy
Requires-Dist: google-datacatalog-connectors-commons (>=0.6.0)
